<annotation>
  <folder>collated_images</folder>
  <filename>000268.jpg</filename>
  <segmented>0</segmented>
  <size>
    <width>570</width>
    <height>462</height>
    <depth>3</depth>
  </size>
  <object>
    <name>saddle</name>
    <pose>Unspecified</pose>
    <truncated>0</truncated>
    <difficult>0</difficult>
    <bndbox>
      <xmin>36</xmin>
      <ymin>13</ymin>
      <xmax>547</xmax>
      <ymax>354</ymax>
    </bndbox>
  </object>
  <object>
    <name>saddle</name>
    <pose>Unspecified</pose>
    <truncated>0</truncated>
    <difficult>0</difficult>
    <bndbox>
      <xmin>36</xmin>
      <ymin>13</ymin>
      <xmax>547</xmax>
      <ymax>354</ymax>
    </bndbox>
  </object>
  <object>
    <name>saddle</name>
    <pose>Unspecified</pose>
    <truncated>0</truncated>
    <difficult>0</difficult>
    <bndbox>
      <xmin>36</xmin>
      <ymin>13</ymin>
      <xmax>547</xmax>
      <ymax>354</ymax>
    </bndbox>
  </object>
</annotation>
